MANIFEST.in
README.rst
setup.cfg
setup.py
Cuckoo.egg-info/PKG-INFO
Cuckoo.egg-info/SOURCES.txt
Cuckoo.egg-info/dependency_links.txt
Cuckoo.egg-info/entry_points.txt
Cuckoo.egg-info/requires.txt
Cuckoo.egg-info/top_level.txt
cuckoo/__init__.py
cuckoo/main.py
cuckoo/misc.py
cuckoo/apps/__init__.py
cuckoo/apps/api.py
cuckoo/apps/apps.py
cuckoo/apps/distributed.py
cuckoo/apps/dnsserve.py
cuckoo/apps/import_.py
cuckoo/apps/rooter.py
cuckoo/auxiliary/__init__.py
cuckoo/auxiliary/mitm.py
cuckoo/auxiliary/reboot.py
cuckoo/auxiliary/replay.py
cuckoo/auxiliary/services.py
cuckoo/auxiliary/sniffer.py
cuckoo/common/__init__.py
cuckoo/common/abstracts.py
cuckoo/common/colors.py
cuckoo/common/compare.py
cuckoo/common/config.py
cuckoo/common/constants.py
cuckoo/common/defines.py
cuckoo/common/dns.py
cuckoo/common/elastic.py
cuckoo/common/exceptions.py
cuckoo/common/files.py
cuckoo/common/irc.py
cuckoo/common/logo.py
cuckoo/common/mongo.py
cuckoo/common/netlog.py
cuckoo/common/objects.py
cuckoo/common/scripting.py
cuckoo/common/shellcode.py
cuckoo/common/structures.py
cuckoo/common/utils.py
cuckoo/common/virustotal.py
cuckoo/common/whitelist.py
cuckoo/compat/__init__.py
cuckoo/compat/config.py
cuckoo/core/__init__.py
cuckoo/core/database.py
cuckoo/core/extract.py
cuckoo/core/feedback.py
cuckoo/core/guest.py
cuckoo/core/init.py
cuckoo/core/log.py
cuckoo/core/plugins.py
cuckoo/core/report.py
cuckoo/core/resultserver.py
cuckoo/core/rooter.py
cuckoo/core/scheduler.py
cuckoo/core/startup.py
cuckoo/core/submit.py
cuckoo/data/__init__.py
cuckoo/data/agent/agent.py
cuckoo/data/agent/agent.sh
cuckoo/data/analyzer/android/analyzer.py
cuckoo/data/analyzer/android/config/hooks.json
cuckoo/data/analyzer/android/lib/__init__.py
cuckoo/data/analyzer/android/lib/api/__init__.py
cuckoo/data/analyzer/android/lib/api/adb.py
cuckoo/data/analyzer/android/lib/api/screenshot.py
cuckoo/data/analyzer/android/lib/common/__init__.py
cuckoo/data/analyzer/android/lib/common/abstracts.py
cuckoo/data/analyzer/android/lib/common/constants.py
cuckoo/data/analyzer/android/lib/common/exceptions.py
cuckoo/data/analyzer/android/lib/common/results.py
