Metadata-Version: 2.1
Name: Cuckoo
Version: 2.0.7
Summary: Automated Malware Analysis System
Home-page: https://cuckoosandbox.org/
Author: Stichting Cuckoo Foundation
Author-email: cuckoo@cuckoofoundation.org
License: GPLv3
Keywords: cuckoo sandbox automated malware analysis project threat intelligence cert soc
Platform: UNKNOWN
Classifier: Development Status :: 5 - Production/Stable
Classifier: Environment :: Console
Classifier: Environment :: Web Environment
Classifier: Framework :: Django
Classifier: Framework :: Flask
Classifier: Framework :: Pytest
Classifier: Intended Audience :: Information Technology
Classifier: Intended Audience :: Science/Research
Classifier: Natural Language :: English
Classifier: License :: OSI Approved :: GNU General Public License v3 (GPLv3)
Classifier: Operating System :: POSIX :: Linux
Classifier: Programming Language :: Python :: 2.7
Classifier: Topic :: Security
Provides-Extra: distributed
Provides-Extra: weasyprint
Provides-Extra: postgresql
